WIPClientPy/__init__.py
WIPClientPy/client.py
WIPClientPy/client_async.py
WIPClientPy/config.ini
WIPClientPy/coordinate_cache.json
WIPCommonPy/__init__.py
WIPCommonPy/clients/__init__.py
WIPCommonPy/clients/location_client.py
WIPCommonPy/clients/query_client.py
WIPCommonPy/clients/report_client.py
WIPCommonPy/clients/weather_client.py
WIPCommonPy/clients/utils/__init__.py
WIPCommonPy/clients/utils/packet_id_generator.py
WIPCommonPy/clients/utils/receive_with_id.py
WIPCommonPy/clients/utils/safe_sock_sendto.py
WIPCommonPy/packet/__init__.py
WIPCommonPy/packet/dynamic_format.py
WIPCommonPy/packet/core/__init__.py
WIPCommonPy/packet/core/bit_utils.py
WIPCommonPy/packet/core/exceptions.py
WIPCommonPy/packet/core/extended_field.py
WIPCommonPy/packet/core/format.py
WIPCommonPy/packet/core/format_base.py
WIPCommonPy/packet/core/format_extended.py
WIPCommonPy/packet/debug/__init__.py
WIPCommonPy/packet/debug/debug_logger.py
WIPCommonPy/packet/format_spec/extended_fields.json
WIPCommonPy/packet/format_spec/request_fields.json
WIPCommonPy/packet/format_spec/response_fields.json
WIPCommonPy/packet/models/request.py
WIPCommonPy/packet/models/response.py
WIPCommonPy/packet/types/error_response.py
WIPCommonPy/packet/types/location_packet.py
WIPCommonPy/packet/types/query_packet.py
WIPCommonPy/packet/types/report_packet.py
WIPCommonPy/utils/__init__.py
WIPCommonPy/utils/auth.py
WIPCommonPy/utils/cache.py
WIPCommonPy/utils/config_loader.py
WIPCommonPy/utils/file_cache.py
WIPCommonPy/utils/log_config.py
WIPCommonPy/utils/network.py
WIPCommonPy/utils/redis_log_handler.py
WIPServerPy/__init__.py
WIPServerPy/data/__init__.py
WIPServerPy/data/alert_processor.py
WIPServerPy/data/create_area_codes_json.py
WIPServerPy/data/disaster_processor.py
WIPServerPy/data/get_alert.py
WIPServerPy/data/get_codes.py
WIPServerPy/data/get_disaster.py
WIPServerPy/data/get_earthquake.py
WIPServerPy/data/get_unified_data.py
WIPServerPy/data/redis_manager.py
WIPServerPy/data/xml_base.py
wiplib-0.1.0.dist-info/licenses/LICENSE
wiplib-0.1.0.dist-info/METADATA
wiplib-0.1.0.dist-info/WHEEL
wiplib-0.1.0.dist-info/top_level.txt
wiplib-0.1.0.dist-info/RECORD
