Metadata-Version: 2.4
Name: wiplib
Version: 0.1.0
Summary: Awesome toolkit for weather data (client‑side).
Author-email: WIP Team <u22.wip.team@gmail.com>
License: MIT License
Project-URL: Homepage, https://github.com/U22-2025/WIP
Keywords: weather,protocol,data,disaster,alert,Japan,toolkit
Classifier: Programming Language :: Python :: 3
Classifier: Programming Language :: Python :: 3 :: Only
Classifier: License :: OSI Approved :: MIT License
Classifier: Operating System :: OS Independent
Requires-Python: >=3.9
License-File: LICENSE
Requires-Dist: requests>=2.32.0
Requires-Dist: aiohttp>=3.9.0
Requires-Dist: websockets>=15.0.1
Requires-Dist: python-dotenv>=1.0.0
Requires-Dist: redis>=6.2.0
Provides-Extra: dev
Requires-Dist: pytest; extra == "dev"
Requires-Dist: pytest-asyncio; extra == "dev"
Requires-Dist: pytest-cov; extra == "dev"
Requires-Dist: pytest-xdist; extra == "dev"
Requires-Dist: black; extra == "dev"
Provides-Extra: location-server
Requires-Dist: psycopg2; extra == "location-server"
Provides-Extra: query-server
Requires-Dist: schedule; extra == "query-server"
Requires-Dist: python-dateutil; extra == "query-server"
Requires-Dist: python-dotenv; extra == "query-server"
Provides-Extra: weather-server
Provides-Extra: report-server
Provides-Extra: servers
Requires-Dist: psycopg2; extra == "servers"
Requires-Dist: redis; extra == "servers"
Requires-Dist: schedule; extra == "servers"
Requires-Dist: python-dateutil; extra == "servers"
Requires-Dist: python-dotenv; extra == "servers"
Provides-Extra: all
Requires-Dist: psycopg2; extra == "all"
Requires-Dist: redis; extra == "all"
Requires-Dist: schedule; extra == "all"
Requires-Dist: python-dateutil; extra == "all"
Requires-Dist: python-dotenv; extra == "all"
Requires-Dist: pytest; extra == "all"
Requires-Dist: pytest-asyncio; extra == "all"
Requires-Dist: pytest-cov; extra == "all"
Requires-Dist: pytest-xdist; extra == "all"
Requires-Dist: black; extra == "all"
Dynamic: license-file
